bairy/__main__.py
bairy/create_service.py
bairy/log_configs.py
bairy/device/app.py
bairy/device/configs.py
bairy/device/dash_plot.py
bairy/device/dash_table.py
bairy/device/device.py
bairy/device/preprocess.py
bairy/device/sensor.py
bairy/device/utils.py
bairy/device/validate.py
bairy/hub/app.py
bairy/hub/configs.py
bairy/hub/dash_plot.py
bairy/hub/request.py
bairy-0.1.8.dist-info/LICENSE.md
bairy-0.1.8.dist-info/METADATA
bairy-0.1.8.dist-info/WHEEL
bairy-0.1.8.dist-info/entry_points.txt
bairy-0.1.8.dist-info/top_level.txt
bairy-0.1.8.dist-info/RECORD
