Metadata-Version: 2.1
Name: bairy
Version: 0.1.8
Summary: Display data from Raspberry Pi.
Home-page: https://github.com/zebengberg/bairy
Author: Zeb Engberg
Author-email: zebengberg@gmail.com
License: MIT
Platform: UNKNOWN
Classifier: License :: OSI Approved :: MIT License
Classifier: Programming Language :: Python :: 3
Classifier: Programming Language :: Python :: 3.7
Classifier: Topic :: Internet :: WWW/HTTP :: WSGI
Classifier: Topic :: Scientific/Engineering :: Visualization
Requires-Python: >=3.7.0
Requires-Dist: uvicorn
Requires-Dist: fastapi
Requires-Dist: pydantic
Requires-Dist: dash
Requires-Dist: plotly
Requires-Dist: pandas
Requires-Dist: nest-asyncio
Requires-Dist: aiohttp
Requires-Dist: smbus2
Requires-Dist: gpiozero
